{
    "Ar36": {
        "error": 0.00016683481256498989,
        "error_type": "",
        "fit": "Average_SD",
        "references": [
            {
                "exclude": "ok",
                "record_id": "bc-02-J-1284",
                "uuid": "967fad04-a9eb-4dbe-b903-9ae6e836915e"
            },
            {
                "exclude": "ok",
                "record_id": "bc-02-J-1285",
                "uuid": "8584089b-9bb3-4085-b2ef-d87470d34770"
            },
            {
                "exclude": "ok",
                "record_id": "bc-02-J-1286",
                "uuid": "07b007b5-e163-43d4-8129-6bff45e4c8e9"
            },
            {
                "exclude": "ok",
                "record_id": "bc-02-J-1287",
                "uuid": "1ac106fc-799c-458e-9b7b-6c68810b23d5"
            },
            {
                "exclude": "omit",
                "record_id": "bc-02-J-1288",
                "uuid": "484438db-2cbf-49e1-be92-6b43dcf4f8cd"
            },
            {
                "exclude": "ok",
                "record_id": "bc-02-J-1290",
                "uuid": "1cdc5bfd-e4f4-4e32-83c3-3cfbf663977a"
            },
            {
                "exclude": "omit",
                "record_id": "bc-02-J-1291",
                "uuid": "d5fd6098-48a5-4a6c-825a-e05d2d33e8b7"
            }
        ],
        "reviewed": true,
        "value": 0.003332977610043359
    },
    "Ar37": {
        "error": 0.00470776187988135,
        "error_type": "",
        "fit": "Weighted Mean_SEM",
        "references": [
            {
                "exclude": "ok",
                "record_id": "bc-02-J-1284",
                "uuid": "967fad04-a9eb-4dbe-b903-9ae6e836915e"
            },
            {
                "exclude": "ok",
                "record_id": "bc-02-J-1285",
                "uuid": "8584089b-9bb3-4085-b2ef-d87470d34770"
            },
            {
                "exclude": "ok",
                "record_id": "bc-02-J-1286",
                "uuid": "07b007b5-e163-43d4-8129-6bff45e4c8e9"
            },
            {
                "exclude": "ok",
                "record_id": "bc-02-J-1287",
                "uuid": "1ac106fc-799c-458e-9b7b-6c68810b23d5"
            },
            {
                "exclude": "omit",
                "record_id": "bc-02-J-1288",
                "uuid": "484438db-2cbf-49e1-be92-6b43dcf4f8cd"
            },
            {
                "exclude": "ok",
                "record_id": "bc-02-J-1290",
                "uuid": "1cdc5bfd-e4f4-4e32-83c3-3cfbf663977a"
            },
            {
                "exclude": "omit",
                "record_id": "bc-02-J-1291",
                "uuid": "d5fd6098-48a5-4a6c-825a-e05d2d33e8b7"
            }
        ],
        "reviewed": true,
        "value": 0.044658083356479826
    },
    "Ar38": {
        "error": 0.001910267456243232,
        "error_type": "",
        "fit": "Weighted Mean_SEM",
        "references": [
            {
                "exclude": "ok",
                "record_id": "bc-02-J-1284",
                "uuid": "967fad04-a9eb-4dbe-b903-9ae6e836915e"
            },
            {
                "exclude": "ok",
                "record_id": "bc-02-J-1285",
                "uuid": "8584089b-9bb3-4085-b2ef-d87470d34770"
            },
            {
                "exclude": "ok",
                "record_id": "bc-02-J-1286",
                "uuid": "07b007b5-e163-43d4-8129-6bff45e4c8e9"
            },
            {
                "exclude": "ok",
                "record_id": "bc-02-J-1287",
                "uuid": "1ac106fc-799c-458e-9b7b-6c68810b23d5"
            },
            {
                "exclude": "omit",
                "record_id": "bc-02-J-1288",
                "uuid": "484438db-2cbf-49e1-be92-6b43dcf4f8cd"
            },
            {
                "exclude": "ok",
                "record_id": "bc-02-J-1290",
                "uuid": "1cdc5bfd-e4f4-4e32-83c3-3cfbf663977a"
            },
            {
                "exclude": "omit",
                "record_id": "bc-02-J-1291",
                "uuid": "d5fd6098-48a5-4a6c-825a-e05d2d33e8b7"
            }
        ],
        "reviewed": true,
        "value": 0.008035815677315657
    },
    "Ar39": {
        "error": 0.003543256013508375,
        "error_type": "",
        "fit": "Weighted Mean_SEM",
        "references": [
            {
                "exclude": "ok",
                "record_id": "bc-02-J-1284",
                "uuid": "967fad04-a9eb-4dbe-b903-9ae6e836915e"
            },
            {
                "exclude": "ok",
                "record_id": "bc-02-J-1285",
                "uuid": "8584089b-9bb3-4085-b2ef-d87470d34770"
            },
            {
                "exclude": "ok",
                "record_id": "bc-02-J-1286",
                "uuid": "07b007b5-e163-43d4-8129-6bff45e4c8e9"
            },
            {
                "exclude": "ok",
                "record_id": "bc-02-J-1287",
                "uuid": "1ac106fc-799c-458e-9b7b-6c68810b23d5"
            },
            {
                "exclude": "omit",
                "record_id": "bc-02-J-1288",
                "uuid": "484438db-2cbf-49e1-be92-6b43dcf4f8cd"
            },
            {
                "exclude": "ok",
                "record_id": "bc-02-J-1290",
                "uuid": "1cdc5bfd-e4f4-4e32-83c3-3cfbf663977a"
            },
            {
                "exclude": "omit",
                "record_id": "bc-02-J-1291",
                "uuid": "d5fd6098-48a5-4a6c-825a-e05d2d33e8b7"
            }
        ],
        "reviewed": true,
        "value": 0.02832410778897793
    },
    "Ar40": {
        "error": 0.02296400136165744,
        "error_type": "",
        "fit": "Average_SD",
        "references": [
            {
                "exclude": "ok",
                "record_id": "bc-02-J-1284",
                "uuid": "967fad04-a9eb-4dbe-b903-9ae6e836915e"
            },
            {
                "exclude": "ok",
                "record_id": "bc-02-J-1285",
                "uuid": "8584089b-9bb3-4085-b2ef-d87470d34770"
            },
            {
                "exclude": "ok",
                "record_id": "bc-02-J-1286",
                "uuid": "07b007b5-e163-43d4-8129-6bff45e4c8e9"
            },
            {
                "exclude": "ok",
                "record_id": "bc-02-J-1287",
                "uuid": "1ac106fc-799c-458e-9b7b-6c68810b23d5"
            },
            {
                "exclude": "omit",
                "record_id": "bc-02-J-1288",
                "uuid": "484438db-2cbf-49e1-be92-6b43dcf4f8cd"
            },
            {
                "exclude": "ok",
                "record_id": "bc-02-J-1290",
                "uuid": "1cdc5bfd-e4f4-4e32-83c3-3cfbf663977a"
            },
            {
                "exclude": "omit",
                "record_id": "bc-02-J-1291",
                "uuid": "d5fd6098-48a5-4a6c-825a-e05d2d33e8b7"
            }
        ],
        "reviewed": true,
        "value": 0.26671824110896314
    },
    "Ar41": {
        "error": 0.013240809039556663,
        "error_type": "",
        "fit": "previous",
        "references": [
            {
                "exclude": false,
                "record_id": "bu-FC-J-9320"
            }
        ],
        "value": 0.017977658377642265
    }
}